relic_engine/__init__.py
relic_engine-0.2.12.dist-info/METADATA
relic_engine-0.2.12.dist-info/WHEEL
relic_engine-0.2.12.dist-info/top_level.txt
relic_engine-0.2.12.dist-info/RECORD
