Metadata-Version: 2.1
Name: relic_engine
Version: 0.2.12
Summary: Engine for generating dictionaries of relics and prime sets.
Author: Jacob McBride
Author-email: jake55111@gmail.com
Keywords: warframe,relics,prime
Classifier: Programming Language :: Python :: 3
Classifier: Operating System :: OS Independent
Requires-Dist: lxml
Requires-Dist: requests
Requires-Dist: bs4
